vhost_master/__init__.py
vhost_master/__main__.py
vhost_master/bruteforce.py
vhost_master/utility.py
vhost_master/vhost_master.py
vhost_master-0.0.4.dist-info/LICENSE
vhost_master-0.0.4.dist-info/METADATA
vhost_master-0.0.4.dist-info/WHEEL
vhost_master-0.0.4.dist-info/entry_points.txt
vhost_master-0.0.4.dist-info/top_level.txt
vhost_master-0.0.4.dist-info/RECORD
