Metadata-Version: 2.1
Name: vhost-master
Version: 0.0.4
Summary: UNKNOWN
Home-page: UNKNOWN
License: UNKNOWN
Platform: UNKNOWN
License-File: LICENSE
Requires-Dist: tldextract
Requires-Dist: colorama
